my_mini_sklearn/__init__.py
my_mini_sklearn/__pycache__/__init__.cpython-39.pyc
my_mini_sklearn/base/__init__.py
my_mini_sklearn/base/data_processing.py
my_mini_sklearn/base/model_evaluation.py
my_mini_sklearn/models/Kmeans.py
my_mini_sklearn/models/LogisticRegression.py
my_mini_sklearn/models/PCA.py
my_mini_sklearn/models/SVM.py
my_mini_sklearn/models/Softmax.py
my_mini_sklearn/models/__init__.py
my_mini_sklearn/models/decision_tree.py
my_mini_sklearn/models/knn.py
my_mini_sklearn/models/linear_regression.py
my_mini_sklearn/models/navi_bayes.py
my_mini_sklearn/models/__pycache__/__init__.cpython-39.pyc
my_mini_sklearn/models/__pycache__/linear_regression.cpython-39.pyc
my_mini_sklearn/utils/__init__.py
my_mini_sklearn/utils/cross_validation.py
my_mini_sklearn/utils/grid_search.py
my_mini_sklearn-0.1.4.dist-info/METADATA
my_mini_sklearn-0.1.4.dist-info/WHEEL
my_mini_sklearn-0.1.4.dist-info/top_level.txt
my_mini_sklearn-0.1.4.dist-info/RECORD
