Metadata-Version: 2.1
Name: my-mini-sklearn
Version: 0.1.4
Summary: A mini machine learning library similar to scikit-learn
Home-page: https://gitee.com/zhao-geyi/mini_sklearn1/tree/mini_sklearn
Author: zhao-geyi
Author-email: 3050945076@qq.com
Classifier: Programming Language :: Python :: 3
Classifier: License :: OSI Approved :: MIT License
Classifier: Operating System :: OS Independent
Requires-Python: >=3.6
Requires-Dist: numpy
Requires-Dist: matplotlib
